{
  "release": "2.1",
  "dtype": "int8",
  "model_operator_total": 524,
  "unique_operator_total": 15,
  "supported_count": 10,
  "unsupported_count": 1,
  "unknown_count": 4,
  "supported": [
    {
      "operator": "Add",
      "count": 73,
      "onnx-opset-version": "14",
      "int8": "Y",
      "bfloat16": "Y",
      "sima_hw_sw_constraints": null,
      "notes": "Can be fused with conv or matmul."
    },
    {
      "operator": "Concat",
      "count": 1,
      "onnx-opset-version": "13",
      "int8": "Y",
      "bfloat16": "Y",
      "sima_hw_sw_constraints": null,
      "notes": null
    },
    {
      "operator": "Conv",
      "count": 1,
      "onnx-opset-version": "11",
      "int8": "Y",
      "bfloat16": "Y",
      "sima_hw_sw_constraints": "dilation = [1, 63] (HW)\nstrides = [1, 31] (HW)",
      "notes": "fused with bias and activation.  ONNX does not have 1D convolution, though we support it for other frontends."
    },
    {
      "operator": "Div",
      "count": 12,
      "onnx-opset-version": "14",
      "int8": "Y",
      "bfloat16": "Y",
      "sima_hw_sw_constraints": null,
      "notes": null
    },
    {
      "operator": "Erf",
      "count": 12,
      "onnx-opset-version": "13",
      "int8": "Y",
      "bfloat16": "Y",
      "sima_hw_sw_constraints": null,
      "notes": null
    },
    {
      "operator": "MatMul",
      "count": 60,
      "onnx-opset-version": "13",
      "int8": "Y",
      "bfloat16": "Y",
      "sima_hw_sw_constraints": null,
      "notes": "Batched MatMul."
    },
    {
      "operator": "Mul",
      "count": 48,
      "onnx-opset-version": "14",
      "int8": "Y",
      "bfloat16": "Y",
      "sima_hw_sw_constraints": null,
      "notes": null
    },
    {
      "operator": "Reshape",
      "count": 109,
      "onnx-opset-version": "14",
      "int8": "Y",
      "bfloat16": "Y",
      "sima_hw_sw_constraints": "allowzero = 0 (SW)\nShape cannot be empty. (SW)",
      "notes": "batch_flatten, expand_dims, and squeeze are converted to reshape, and they are supported if the reshape operator is supported"
    },
    {
      "operator": "Softmax",
      "count": 12,
      "onnx-opset-version": "13",
      "int8": "Y",
      "bfloat16": "Y",
      "sima_hw_sw_constraints": null,
      "notes": null
    },
    {
      "operator": "Transpose",
      "count": 97,
      "onnx-opset-version": "13",
      "int8": "Y",
      "bfloat16": "Y",
      "sima_hw_sw_constraints": null,
      "notes": null
    }
  ],
  "unsupported": [
    {
      "operator": "Gather",
      "count": 37,
      "onnx-opset-version": "13",
      "int8": "N",
      "bfloat16": "Y",
      "sima_hw_sw_constraints": "Indices must be a constant, and it must be 0D or 1D. (HW)",
      "notes": "Converted to slice or conv2d."
    }
  ],
  "unknown": [
    {
      "operator": "Gemm",
      "count": 13,
      "onnx-opset-version": null,
      "int8": null,
      "bfloat16": null,
      "sima_hw_sw_constraints": null,
      "notes": null
    },
    {
      "operator": "LayerNormalization",
      "count": 25,
      "onnx-opset-version": null,
      "int8": null,
      "bfloat16": null,
      "sima_hw_sw_constraints": null,
      "notes": null
    },
    {
      "operator": "Squeeze",
      "count": 12,
      "onnx-opset-version": null,
      "int8": null,
      "bfloat16": null,
      "sima_hw_sw_constraints": null,
      "notes": null
    },
    {
      "operator": "Unsqueeze",
      "count": 12,
      "onnx-opset-version": null,
      "int8": null,
      "bfloat16": null,
      "sima_hw_sw_constraints": null,
      "notes": null
    }
  ]
}
